Metadata-Version: 1.1
Name: p4
Version: 0.1.5
Summary: A Python Pre-Processor for the Processing system
Home-page: https://github.com/benweedon/p4
Author: Ben Weedon
Author-email: ben.weedon@outlook.com
License: GPLv3
Keywords: processing,generative,artwork,art
Platform: UNKNOWN
Classifier: Programming Language :: Python
Classifier: Programming Language :: Python :: 3.2
Classifier: Programming Language :: Python :: 3.3
Classifier: Programming Language :: Python :: 3.4
Classifier: Programming Language :: Python :: 3.5
Classifier: Programming Language :: Python :: 3.6
Classifier: Development Status :: 4 - Beta
Classifier: Environment :: Console
Classifier: Intended Audience :: Developers
Classifier: License :: OSI Approved :: GNU General Public License v3 (GPLv3)
Classifier: Topic :: Artistic Software
Classifier: Topic :: Multimedia :: Graphics
